gate.v
module gate (input [3:0] a, b,
              output [3:0] y1, y2,y3,y4,y5);

assign y1 = a & b; //and
assign y2 = a | b; //or
assign y3 = a ^ b; //xor
assign y4 = ~(a & b); //nand
assign y5 = ~(a | b); //nor

endmodule

gate_tb.v
`timescale 1ns/1ps

module gate_tb;
    reg  [3:0] a,b;
    wire [3:0] y1, y2, y3, y4, y5;

    // Instantiate the Unit Under Test (UUT)
    gate uut (
        .a(a),
        .b(b),
        .y1(y1),
        .y2(y2),
        .y3(y3),
        .y4(y4),
        .y5(y5)
    );

    initial begin
        $display("Starting simulation...");
        $display(" a    |b    |  y1  |  y2  |  y3  |  y4  |  y5  ");
        $display("------|------");

        // Test all 16 combinations (0000 ~ 1111)
        a = 4'b0000; b= 4'b0000; #10; $display("%b | %b| %b| %b| %b| %b| %b", a,b , y1, y2, y3, y4, y5);
        a = 4'b0001; b= 4'b0000; #10; $display("%b | %b| %b| %b| %b| %b| %b", a,b , y1, y2, y3, y4, y5);
        a = 4'b0010; b= 4'b0000; #10; $display("%b | %b| %b| %b| %b| %b| %b", a,b , y1, y2, y3, y4, y5);
        a = 4'b0011; b= 4'b0000; #10; $display("%b | %b| %b| %b| %b| %b| %b", a,b , y1, y2, y3, y4, y5);
        a = 4'b0100; b= 4'b0000; #10; $display("%b | %b| %b| %b| %b| %b| %b", a,b , y1, y2, y3, y4, y5);
        a = 4'b0101; b= 4'b0000; #10; $display("%b | %b| %b| %b| %b| %b| %b", a,b , y1, y2, y3, y4, y5);
        a = 4'b0000; b= 4'b1111; #10; $display("%b | %b| %b| %b| %b| %b| %b", a,b , y1, y2, y3, y4, y5);
        a = 4'b0001; b= 4'b1111; #10; $display("%b | %b| %b| %b| %b| %b| %b", a,b , y1, y2, y3, y4, y5);
        a = 4'b0010; b= 4'b1111; #10; $display("%b | %b| %b| %b| %b| %b| %b", a,b , y1, y2, y3, y4, y5);
        a = 4'b0011; b= 4'b1111; #10; $display("%b | %b| %b| %b| %b| %b| %b", a,b , y1, y2, y3, y4, y5);
        a = 4'b0100; b= 4'b1111; #10; $display("%b | %b| %b| %b| %b| %b| %b", a,b , y1, y2, y3, y4, y5);
        a = 4'b0101; b= 4'b1111; #10; $display("%b | %b| %b| %b| %b| %b| %b", a,b , y1, y2, y3, y4, y5);


        $display("Simulation finished.");
        $finish;
    end

    // For GTKWave waveform viewing
    initial begin
        $dumpfile("gate_tb.vcd");
        $dumpvars(0, gate_tb);
    end
endmodule

gate_tb.vcd
$date
	Fri Jun 26 12:22:50 2026
$end
$version
	Icarus Verilog
$end
$timescale
	1ps
$end
$scope module gate_tb $end
$var wire 4 ! y5 [3:0] $end
$var wire 4 " y4 [3:0] $end
$var wire 4 # y3 [3:0] $end
$var wire 4 $ y2 [3:0] $end
$var wire 4 % y1 [3:0] $end
$var reg 4 & a [3:0] $end
$var reg 4 ' b [3:0] $end
$scope module uut $end
$var wire 4 ( a [3:0] $end
$var wire 4 ) b [3:0] $end
$var wire 4 * y1 [3:0] $end
$var wire 4 + y2 [3:0] $end
$var wire 4 , y3 [3:0] $end
$var wire 4 - y4 [3:0] $end
$var wire 4 . y5 [3:0] $end
$upscope $end
$upscope $end
$enddefinitions $end
$comment Show the parameter values. $end
$dumpall
$end
#0
$dumpvars
b1111 .
b1111 -
b0 ,
b0 +
b0 *
b0 )
b0 (
b0 '
b0 &
b0 %
b0 $
b0 #
b1111 "
b1111 !
$end
#10000
b1110 !
b1110 .
b1 $
b1 +
b1 #
b1 ,
b1 &
b1 (
#20000
b1101 !
b1101 .
b10 $
b10 +
b10 #
b10 ,
b10 &
b10 (
#30000
b1100 !
b1100 .
b11 $
b11 +
b11 #
b11 ,
b11 &
b11 (
#40000
b1011 !
b1011 .
b100 $
b100 +
b100 #
b100 ,
b100 &
b100 (
#50000
b1010 !
b1010 .
b101 $
b101 +
b101 #
b101 ,
b101 &
b101 (
#60000
b0 !
b0 .
b1111 $
b1111 +
b1111 #
b1111 ,
b1111 '
b1111 )
b0 &
b0 (
#70000
b1110 "
b1110 -
b1 %
b1 *
b1110 #
b1110 ,
b1 &
b1 (
#80000
b1101 "
b1101 -
b10 %
b10 *
b1101 #
b1101 ,
b10 &
b10 (
#90000
b1100 "
b1100 -
b11 %
b11 *
b1100 #
b1100 ,
b11 &
b11 (
#100000
b1011 "
b1011 -
b100 %
b100 *
b1011 #
b1011 ,
b100 &
b100 (
#110000
b1010 "
b1010 -
b101 %
b101 *
b1010 #
b1010 ,
b101 &
b101 (
