sillyfunction.v
module sillyfunction (input a, b, c,
                      output y );
    assign y = ~a & ~b & ~c |
                a & ~b & ~c |
                a & ~b & c;
endmodule

sillyfunction_tb.v
`timescale 1ns/1ps

module sillyfunction_tb;
    reg a, b, c;
    wire y;

    // Instantiate the Unit Under Test (UUT)
    sillyfunction uut (
        .a(a),
        .b(b),
        .c(c),
        .y(y)
    );

    initial begin
        $display("Starting simulation...");
        $display("a b c | y");
        $display("------|--");

        // Test all combinations
        a = 0; b = 0; c = 0; #10; $display("%b %b %b | %b", a, b, c, y);
        a = 0; b = 0; c = 1; #10; $display("%b %b %b | %b", a, b, c, y);
        a = 0; b = 1; c = 0; #10; $display("%b %b %b | %b", a, b, c, y);
        a = 0; b = 1; c = 1; #10; $display("%b %b %b | %b", a, b, c, y);
        a = 1; b = 0; c = 0; #10; $display("%b %b %b | %b", a, b, c, y);
        a = 1; b = 0; c = 1; #10; $display("%b %b %b | %b", a, b, c, y);
        a = 1; b = 1; c = 0; #10; $display("%b %b %b | %b", a, b, c, y);
        a = 1; b = 1; c = 1; #10; $display("%b %b %b | %b", a, b, c, y);
        
        $display("Simulation finished.");
        $finish;
    end

    // For GTKWave waveform viewing
    initial begin
        $dumpfile("sillyfunction_tb.vcd");
        $dumpvars(0, sillyfunction_tb);
    end
endmodule

sillyfunction_tb.vcd
$date
	Thu May 14 09:19:27 2026
$end
$version
	Icarus Verilog
$end
$timescale
	1ps
$end
$scope module sillyfunction_tb $end
$var wire 1 ! y $end
$var reg 1 " a $end
$var reg 1 # b $end
$var reg 1 $ c $end
$scope module uut $end
$var wire 1 " a $end
$var wire 1 # b $end
$var wire 1 $ c $end
$var wire 1 ! y $end
$upscope $end
$upscope $end
$enddefinitions $end
$comment Show the parameter values. $end
$dumpall
$end
#0
$dumpvars
0$
0#
0"
1!
$end
#10000
0!
1$
#20000
0$
1#
#30000
1$
#40000
1!
0$
0#
1"
#50000
1$
#60000
0!
0$
1#
#70000
1$
